agent_cover/__init__.py
agent_cover/cli.py
agent_cover/config.py
agent_cover/context.py
agent_cover/discovery.py
agent_cover/instrumentation/__init__.py
agent_cover/instrumentation/agents/__init__.py
agent_cover/instrumentation/agents/patcher.py
agent_cover/instrumentation/agents/targets.py
agent_cover/instrumentation/analyzer.py
agent_cover/instrumentation/base.py
agent_cover/instrumentation/callbacks.py
agent_cover/instrumentation/definitions.py
agent_cover/instrumentation/llm_providers/__init__.py
agent_cover/instrumentation/llm_providers/patcher.py
agent_cover/instrumentation/llm_providers/targets.py
agent_cover/instrumentation/promptflow/__init__.py
agent_cover/instrumentation/promptflow/patcher.py
agent_cover/instrumentation/promptflow/scanner.py
agent_cover/instrumentation/promptflow/targets.py
agent_cover/instrumentation/prompts/__init__.py
agent_cover/instrumentation/prompts/patcher.py
agent_cover/instrumentation/prompts/targets.py
agent_cover/instrumentation/raw_strings/__init__.py
agent_cover/instrumentation/raw_strings/scanner.py
agent_cover/instrumentation/strategies.py
agent_cover/instrumentation/structures/__init__.py
agent_cover/instrumentation/structures/adapters.py
agent_cover/instrumentation/structures/scanner.py
agent_cover/instrumentation/tools/__init__.py
agent_cover/instrumentation/tools/patcher.py
agent_cover/instrumentation/tools/targets.py
agent_cover/manager.py
agent_cover/messages.py
agent_cover/plugin.py
agent_cover/registry.py
agent_cover/reporting/__init__.py
agent_cover/reporting/html.py
agent_cover/reporting/xml.py
agent_cover/sdk.py
agent_cover/utils.py
agent_cover-0.1.1.dist-info/METADATA
agent_cover-0.1.1.dist-info/WHEEL
agent_cover-0.1.1.dist-info/entry_points.txt
agent_cover-0.1.1.dist-info/licenses/LICENSE
agent_cover-0.1.1.dist-info/RECORD
