Metadata-Version: 2.4
Name: agent-cover
Version: 0.1.1
Summary: Framework-agnostic coverage testing and observability tool for LLM Agents.
License: MIT
License-File: LICENSE
Keywords: llm,agent,ai,genai,generative-ai,llmops,llm-ops,genai-ops,mlops,devops-for-ai,testing,coverage,observability,metrics,quality-assurance,qa,evaluation,evals,prompt-engineering,prompt-coverage,tool-coverage,decision-coverage,pytest,plugin,langchain,llama-index,promptflow,openai,promptflow-batch,pf-run
Author: Vittorio Mussin
Author-email: vittorio.mussin@hotmail.it
Requires-Python: >=3.10,<4.0
Classifier: Development Status :: 3 - Alpha
Classifier: Environment :: Console
Classifier: Environment :: Plugins
Classifier: Framework :: Pytest
Classifier: Intended Audience :: Developers
Classifier: Intended Audience :: Information Technology
Classifier: Intended Audience :: Science/Research
Classifier: License :: OSI Approved :: MIT License
Classifier: Operating System :: OS Independent
Classifier: Programming Language :: Python :: 3
Classifier: Programming Language :: Python :: 3.10
Classifier: Programming Language :: Python :: 3.11
Classifier: Programming Language :: Python :: 3.12
Classifier: Programming Language :: Python :: 3.13
Classifier: Programming Language :: Python :: 3.14
Classifier: Topic :: Scientific/Engineering :: Artificial Intelligence
Classifier: Topic :: Software Development :: Libraries :: Python Modules
Classifier: Topic :: Software Development :: Quality Assurance
Classifier: Topic :: Software Development :: Testing
Classifier: Topic :: System :: Monitoring
Classifier: Typing :: Typed
Provides-Extra: all
Provides-Extra: langchain
Provides-Extra: llama-index
Provides-Extra: openai
Provides-Extra: promptflow
Requires-Dist: filelock (>=3.20.1,<4.0.0)
Requires-Dist: langchain (>=0.3.0,<0.4.0) ; extra == "langchain" or extra == "all"
Requires-Dist: llama-index (>=0.13,<0.14) ; extra == "llama-index" or extra == "all"
Requires-Dist: openai (>=1.30.0,<2.0.0) ; extra == "openai" or extra == "all"
Requires-Dist: packaging (>=23.0,<24.0)
Requires-Dist: promptflow (>=1.0.0,<2.0.0) ; extra == "promptflow" or extra == "all"
Requires-Dist: pyyaml (>=6.0,<7.0)
Project-URL: Repository, https://github.com/vittoriomussin/agent-cover
